janusexp/__init__.py
janusexp/_modidx.py
janusexp/_nbdev.py
janusexp/config.py
janusexp/data/JANUS_RM_coeff_20190110_data.qsig
janusexp/data/signal_f4_dn.txt
janusexp/data/spectral_radiance_f4.txt
janusexp/hardware_data/Flight mirror reflectivity.xlsx
janusexp/hardware_data/JANUS_spektral Daten_selection_Leonardo.xlsx
janusexp/hardware_data/PFM FPM Windows Transmission v1.xlsx
janusexp/hardware_data/Report JANUS lenses.xlsx
janusexp/hardware_data/correction_factor_qe_temperature.txt
janusexp/hardware_data/detector_QE.xlsx
janusexp/radiometry/__init__.py
janusexp/radiometry/io.py
janusexp-0.1.0.dist-info/METADATA
janusexp-0.1.0.dist-info/WHEEL
janusexp-0.1.0.dist-info/entry_points.txt
janusexp-0.1.0.dist-info/top_level.txt
janusexp-0.1.0.dist-info/RECORD
