Metadata-Version: 2.1
Name: janusexp
Version: 0.1.0
Summary: Exposure time calculation tools for JANUS instrument
Home-page: https://www.ict.inaf.it/gitlab/juice-janus/janus-nbexposure
Author: Michael Aye and Livio Agostini and Luca Penasa
Author-email: michael.aye@fu-berlin.de
License: MIT License
Keywords: nbdev jupyter notebook python
Classifier: Development Status :: 4 - Beta
Classifier: Intended Audience :: Developers
Classifier: Natural Language :: English
Classifier: Programming Language :: Python :: 3.10
Classifier: License :: OSI Approved :: MIT License
Requires-Python: >=3.10
Requires-Dist: pandas
Provides-Extra: dev
